memmod/__init__.py
memmod/_memmod.pyd
memmod/tests/StrQueue-win32.dll
memmod/tests/__init__.py
memmod/tests/test_memmod.py
memmod-1.1.0.dist-info/LICENSE.txt
memmod-1.1.0.dist-info/METADATA
memmod-1.1.0.dist-info/WHEEL
memmod-1.1.0.dist-info/top_level.txt
memmod-1.1.0.dist-info/RECORD
